minty_infra_storage/__init__.py
minty_infra_storage/py.typed
minty_infra_storage/s3.py
minty_infra_storage-3.0.1.dist-info/METADATA
minty_infra_storage-3.0.1.dist-info/WHEEL
minty_infra_storage-3.0.1.dist-info/top_level.txt
minty_infra_storage-3.0.1.dist-info/RECORD
