Metadata-Version: 2.1
Name: minty-infra-storage
Version: 3.0.1
Summary: Storage infrastructure for the Minty framework
Home-page: https://gitlab.com/minty-python/minty-infra-storage
Author: Martijn van de Streek
Author-email: martijn@mintlab.nl
License: EUPL license
Keywords: minty_infra_storage
Platform: UNKNOWN
Classifier: Development Status :: 2 - Pre-Alpha
Classifier: Intended Audience :: Developers
Classifier: License :: OSI Approved :: European Union Public Licence 1.2 (EUPL 1.2)
Classifier: Natural Language :: English
Classifier: Programming Language :: Python :: 3.9
Requires-Dist: minty (~=3.0)
Requires-Dist: minio (~=7.0)
